.DS_Store
pyplin/__init__.py
pyplin/pipe.py
pyplin/test_pipe.py
pyplin-0.13.dist-info/DESCRIPTION.rst
pyplin-0.13.dist-info/METADATA
pyplin-0.13.dist-info/RECORD
pyplin-0.13.dist-info/WHEEL
pyplin-0.13.dist-info/metadata.json
pyplin-0.13.dist-info/top_level.txt
