Metadata-Version: 2.0
Name: pyplin
Version: 0.13
Summary: overloading | to implement pipe
Home-page: https://github.com/willhyper/pyplin.git
Author: Chao-Wei Chen
Author-email: willhyper@gmail.com
License: MIT
Download-URL: https://github.com/willhyper/pyplin/archive/master.zip
Keywords: pipe,pipeline
Platform: UNKNOWN
